deterministic_zip_go-5.2.0.dist-info/METADATA
deterministic_zip_go-5.2.0.dist-info/WHEEL
deterministic_zip_go-5.2.0.dist-info/entry_points.txt
deterministic_zip_go/__init__.py
deterministic_zip_go/__main__.py
deterministic_zip_go/deterministic-zip
deterministic_zip_go/exec.py
deterministic_zip_go-5.2.0.dist-info/RECORD
