Metadata-Version: 2.1
Name: deterministic-zip-go
Version: 5.2.0
Summary: deterministic-zip wrapped for usage with pip and/or python.
License: MIT
Classifier: Development Status :: 5 - Production/Stable
Classifier: Intended Audience :: Developers
Classifier: Environment :: Console
Classifier: Environment :: MacOS X
Classifier: Operating System :: POSIX
Classifier: Operating System :: Unix
Classifier: Environment :: Win32 (MS Windows)
Classifier: Programming Language :: Python :: 3
Classifier: Programming Language :: Python :: 3.8
Classifier: Programming Language :: Python :: 3.9
Classifier: Programming Language :: Python :: 3.10
Classifier: Programming Language :: Python :: 3.11
Classifier: Programming Language :: Python :: 3.12
Project-URL: Homepage, https://github.com/timo-reymann/deterministic-zip
Project-URL:
Project-URL: Bug Tracker, https://github.com/timo-reymann/deterministic-zip
Requires-Python: >=3.8
